.gitignore
INSTALL.txt
LICENSE.txt
MANIFEST.in
README.txt
setup.py
src/gitserve/__init__.py
src/gitserve/gitweb.cgi
src/gitserve/gitweb.conf
src/gitserve.egg-info/PKG-INFO
src/gitserve.egg-info/SOURCES.txt
src/gitserve.egg-info/dependency_links.txt
src/gitserve.egg-info/entry_points.txt
src/gitserve.egg-info/not-zip-safe
src/gitserve.egg-info/top_level.txt
src/gitserve/media/git-favicon.png
src/gitserve/media/git-logo.png
src/gitserve/media/gitweb.css