Metadata-Version: 1.0
Name: gitserve
Version: 0.2.0
Summary: A helper tool for git that mimics mercurial's serve command
Home-page: http://github.com/jezdez/git-serve/
Author: Jannis Leidel
Author-email: jannis@leidel.info
License: GPL-2
Keywords: git dvcs mercurial serve cgi
Platform: UNKNOWN
Classifier: Development Status :: 3 - Alpha
Classifier: Environment :: Console
Classifier: Environment :: No Input/Output (Daemon)
Classifier: Intended Audience :: Developers
Classifier: Intended Audience :: End Users/Desktop
Classifier: License :: OSI Approved :: GNU General Public License (GPL)
Classifier: Operating System :: OS Independent
Classifier: Programming Language :: Python
Classifier: Topic :: Software Development :: Version Control
Classifier: Topic :: Internet :: WWW/HTTP :: Dynamic Content
Classifier: Topic :: Internet :: WWW/HTTP :: HTTP Servers
